pycit/__init__.py
pycit/ci_test.py
pycit/markov_blanket.py
pycit/preprocessing.py
pycit/estimators/__init__.py
pycit/estimators/bi_ksg_cmi.py
pycit/estimators/bi_ksg_mi.py
pycit/estimators/kl_entropy.py
pycit/estimators/ksg_cmi.py
pycit/estimators/ksg_mi.py
pycit/estimators/mixed_cmi.py
pycit/estimators/mixed_mi.py
pycit/testers/__init__.py
pycit/testers/base_hypothesis_test.py
pycit/testers/conditional_independence_test.py
pycit/testers/independence_test.py
pycit-0.0.7.dist-info/LICENSE
pycit-0.0.7.dist-info/METADATA
pycit-0.0.7.dist-info/WHEEL
pycit-0.0.7.dist-info/top_level.txt
pycit-0.0.7.dist-info/RECORD
