Metadata-Version: 2.1
Name: pycit
Version: 0.0.7
Summary: Conditional independence testing and Markov blanket feature selection in Python
Home-page: https://github.com/syanga/pycit
Author: Alan Yang
Author-email: ayang1097@gmail.com
License: UNKNOWN
Platform: UNKNOWN
Classifier: Programming Language :: Python :: 3
Classifier: License :: OSI Approved :: MIT License
Requires-Python: >=3.6
Requires-Dist: scipy (>=1.4.1)
Requires-Dist: numpy (>=1.17.4)
Requires-Dist: scikit-learn (>=0.22.1)
